MagicProgress/MagicProgress.py
MagicProgress/__init__.py
MagicProgress-0.0.4.dist-info/LICENSE
MagicProgress-0.0.4.dist-info/METADATA
MagicProgress-0.0.4.dist-info/WHEEL
MagicProgress-0.0.4.dist-info/top_level.txt
MagicProgress-0.0.4.dist-info/RECORD
