Metadata-Version: 2.1
Name: MagicProgress
Version: 0.0.4
Summary: Python Magic Progressbar
Home-page: UNKNOWN
Author: Kia Hamedi
Author-email: <kia.arta9793@gmail.com>
License: UNKNOWN
Project-URL: Homepage, https://github.com/kiahamedi/MagicProgress
Project-URL: Website, https://kiahamedi.ir/magic-progress/
Keywords: python,progress,progressbar,magic progress,kia hamedi
Platform: UNKNOWN
Classifier: Development Status :: 1 - Planning
Classifier: Intended Audience :: Developers
Classifier: Programming Language :: Python :: 3
Classifier: Operating System :: Unix
Classifier: Operating System :: MacOS :: MacOS X
Classifier: Operating System :: Microsoft :: Windows
License-File: LICENSE
